{
    "id": "https://iiif.chartes.psl.eu/encprom/encprom_1907-1908_1_1/manifest",
    "type": "Manifest",
    "@context": "http://iiif.io/api/presentation/3/context.json",
    "label": {
        "fr": [
            "Photographie numéro 1 des 1907-1908ème année de l'année 1907-1908 l'École nationale des chartes"
        ]
    },
    "thumbnail": [
        {
            "id": "https://iiif.chartes.psl.eu/images/encprom/encprom_1907-1908_1_1/encprom_1907-1908_1_1_1.jpg/full/180,/0/default.jpg",
            "type": "Image",
            "format": "image/jpeg",
            "service": [
                {
                    "id": "https://iiif.chartes.psl.eu/images/encprom/encprom_1907-1908_1_1/encprom_1907-1908_1_1_1.jpg",
                    "type": "ImageService2",
                    "profile": "level2"
                }
            ]
        }
    ],
    "requiredStatement": {
        "label": {
            "en": [
                "Attribution"
            ]
        },
        "value": {
            "en": [
                "Provided courtesy of École nationale des chartes"
            ]
        }
    },
    "rights": "http://creativecommons.org/licenses/by-sa/4.0/",
    "provider": [
        {
            "id": "https://www.wikidata.org/wiki/Q273570",
            "type": "Agent",
            "label": {
                "fr": [
                    "École nationale des chartes"
                ]
            },
            "homepage": [
                {
                    "id": "http://www.chartes.psl.eu/",
                    "type": "Text",
                    "label": {
                        "fr": [
                            "Accueil du site de l’École des chartes"
                        ]
                    },
                    "format": "text/html"
                }
            ],
            "logo": [
                {
                    "id": "https://iiif.chartes.psl.eu/images/enc/logo-enc.png/full/full/0/default.png",
                    "type": "Image",
                    "format": "image/png",
                    "height": 302,
                    "width": 70,
                    "service": [
                        {
                            "id": "https://iiif.chartes.psl.eu/images/enc/logo-enc.png",
                            "type": "ImageService2",
                            "profile": "level2"
                        }
                    ]
                }
            ]
        }
    ],
    "partOf": [
        {
            "id": "https://iiif.chartes.psl.eu/encprom/collection/encprom_1907-1908",
            "type": "Collection"
        }
    ],
    "start": {
        "id": "https://iiif.chartes.psl.eu/encprom/encprom_1907-1908_1_1/canvas/f1",
        "type": "Canvas"
    },
    "metadata": [
        {
            "label": {
                "fr": [
                    "Titre"
                ]
            },
            "value": {
                "fr": [
                    "Photographie numéro 1 des 1907-1908ème année de l'année 1907-1908 l'École nationale des chartes"
                ]
            }
        },
        {
            "label": {
                "fr": [
                    "date"
                ]
            },
            "value": {
                "fr": [
                    "1907-1908"
                ]
            }
        }
    ],
    "items": [
        {
            "id": "https://iiif.chartes.psl.eu/encprom/encprom_1907-1908_1_1/canvas/f1",
            "type": "Canvas",
            "label": {
                "none": [
                    "recto"
                ]
            },
            "items": [
                {
                    "id": "https://iiif.chartes.psl.eu/encprom/encprom_1907-1908_1_1/annotation-page/p1",
                    "type": "AnnotationPage",
                    "items": [
                        {
                            "id": "https://iiif.chartes.psl.eu/encprom/encprom_1907-1908_1_1/annotation/a1",
                            "type": "Annotation",
                            "motivation": "painting",
                            "target": "https://iiif.chartes.psl.eu/encprom/encprom_1907-1908_1_1/canvas/f1",
                            "body": {
                                "id": "https://iiif.chartes.psl.eu/images/encprom/encprom_1907-1908_1_1/encprom_1907-1908_1_1_1.jpg/full/full/0/default.jpg",
                                "type": "Image",
                                "format": "image/jpeg",
                                "service": [
                                    {
                                        "id": "https://iiif.chartes.psl.eu/images/encprom/encprom_1907-1908_1_1/encprom_1907-1908_1_1_1.jpg",
                                        "type": "ImageService2",
                                        "profile": "level2"
                                    }
                                ]
                            },
                            "on": "https://iiif.chartes.psl.eu/encprom/encprom_1907-1908_1_1/canvas/f1"
                        }
                    ]
                }
            ],
            "height": 2390,
            "width": 2770
        },
        {
            "id": "https://iiif.chartes.psl.eu/encprom/encprom_1907-1908_1_1/canvas/f2",
            "type": "Canvas",
            "label": {
                "none": [
                    "verso"
                ]
            },
            "items": [
                {
                    "id": "https://iiif.chartes.psl.eu/encprom/encprom_1907-1908_1_1/annotation-page/p2",
                    "type": "AnnotationPage",
                    "items": [
                        {
                            "id": "https://iiif.chartes.psl.eu/encprom/encprom_1907-1908_1_1/annotation/a2",
                            "type": "Annotation",
                            "motivation": "painting",
                            "target": "https://iiif.chartes.psl.eu/encprom/encprom_1907-1908_1_1/canvas/f2",
                            "body": {
                                "id": "https://iiif.chartes.psl.eu/images/encprom/encprom_1907-1908_1_1/encprom_1907-1908_1_1_2.jpg/full/full/0/default.jpg",
                                "type": "Image",
                                "format": "image/jpeg",
                                "service": [
                                    {
                                        "id": "https://iiif.chartes.psl.eu/images/encprom/encprom_1907-1908_1_1/encprom_1907-1908_1_1_2.jpg",
                                        "type": "ImageService2",
                                        "profile": "level2"
                                    }
                                ]
                            },
                            "on": "https://iiif.chartes.psl.eu/encprom/encprom_1907-1908_1_1/canvas/f2"
                        }
                    ]
                }
            ],
            "height": 2852,
            "width": 3507
        }
    ]
}